fertig/__init__.py
fertig/main.py
tests/__init__.py
tests/test_main.py
fertig-1.0.0a0.dist-info/LICENSE
fertig-1.0.0a0.dist-info/METADATA
fertig-1.0.0a0.dist-info/WHEEL
fertig-1.0.0a0.dist-info/top_level.txt
fertig-1.0.0a0.dist-info/RECORD
