Metadata-Version: 2.1
Name: fertig
Version: 1.0.0a0
Summary: fertig
Author-email: Nathaniel Schaaf <nathaniel.schaaf@gmail.com>
License: Apache Software License
Project-URL: Homepage, https://github.com/schana/fertig
Project-URL: Issues, https://github.com/schana/fertig/issues
Classifier: Development Status :: 2 - Pre-Alpha
Classifier: License :: OSI Approved :: Apache Software License
Classifier: Programming Language :: Python :: 3
Classifier: Programming Language :: Python :: 3.9
Classifier: Programming Language :: Python :: 3.10
Classifier: Programming Language :: Python :: 3.11
Classifier: Typing :: Typed
Requires-Python: >=3.9
License-File: LICENSE
Provides-Extra: dev
Requires-Dist: black ; extra == 'dev'
Requires-Dist: isort ; extra == 'dev'
Requires-Dist: tox ; extra == 'dev'
Requires-Dist: pytest ; extra == 'dev'
